pyredisutils/__init__.py
pyredisutils/_decorators.py
pyredisutils/_settings.py
py_redis_utils-2.0.5.dist-info/METADATA
py_redis_utils-2.0.5.dist-info/WHEEL
py_redis_utils-2.0.5.dist-info/top_level.txt
py_redis_utils-2.0.5.dist-info/RECORD
