Metadata-Version: 2.1
Name: py-redis-utils
Version: 2.0.5
Summary: Utilities with Redis
Home-page: UNKNOWN
Author: KE
Author-email: 
License: UNKNOWN
Keywords: python,flask,PyJWT,decorator,token
Platform: UNKNOWN
Classifier: Development Status :: 1 - Planning
Classifier: Intended Audience :: Developers
Classifier: Programming Language :: Python :: 3.11
Classifier: Operating System :: Unix
Classifier: Operating System :: MacOS
Requires-Dist: PyJWT (>=2.0.0)
Requires-Dist: deepdiff (>=6.2.1)
Requires-Dist: flask (<=2.2.3,>=2.0.0)
Requires-Dist: redis (>=4.5.0)
